pandashape/PandaShaper.py
pandashape/__init__.py
pandashape/describers/CorrelationDescriber.py
pandashape/describers/DTypesDescriber.py
pandashape/describers/Describer.py
pandashape/describers/DistributionDescriber.py
pandashape/describers/GeneralDescriber.py
pandashape/describers/GenericDescriber.py
pandashape/describers/LabelCounter.py
pandashape/describers/__init__.py
pandashape/enums/Columns.py
pandashape/enums/Scaling.py
pandashape/enums/__init__.py
pandashape/internal/ColumnResolver.py
pandashape/internal/DescriberExecutor.py
pandashape/internal/TransformerExecutor.py
pandashape/internal/__init__.py
pandashape/internal/listify.py
pandashape/transformers/CategoricalEncoder.py
pandashape/transformers/GenericTransformer.py
pandashape/transformers/MassLabelEncoder.py
pandashape/transformers/MassScaler.py
pandashape/transformers/Transformer.py
pandashape/transformers/__init__.py
src/__init__.py
src/pandashape/PandaShaper.py
src/pandashape/__init__.py
src/pandashape/describers/CategoricalDescriber.py
src/pandashape/describers/CorrelationDescriber.py
src/pandashape/describers/DTypesDescriber.py
src/pandashape/describers/Describer.py
src/pandashape/describers/DistributionDescriber.py
src/pandashape/describers/GeneralDescriber.py
src/pandashape/describers/LabelCounter.py
src/pandashape/describers/__init__.py
src/pandashape/enums/Columns.py
src/pandashape/enums/Scaling.py
src/pandashape/enums/__init__.py
src/pandashape/internal/ColumnResolver.py
src/pandashape/internal/DescriberExecutor.py
src/pandashape/internal/TransformerExecutor.py
src/pandashape/internal/__init__.py
src/pandashape/internal/listify.py
src/pandashape/transformers/CategoricalEncoder.py
src/pandashape/transformers/MassScaler.py
src/pandashape/transformers/Transformer.py
src/pandashape/transformers/__init__.py
pandashape-0.0.7.dist-info/LICENSE
pandashape-0.0.7.dist-info/METADATA
pandashape-0.0.7.dist-info/WHEEL
pandashape-0.0.7.dist-info/top_level.txt
pandashape-0.0.7.dist-info/RECORD
