Metadata-Version: 2.1
Name: pandashape
Version: 0.0.7
Summary: A package designed to simplify data preprocessing for use with Pandas
Home-page: https://github.com/jammerware/pandashape.git
Author: Ben Stein
Author-email: ben.s.stein@gmail.com
License: UNKNOWN
Platform: UNKNOWN
Classifier: Programming Language :: Python :: 3
Classifier: License :: OSI Approved :: MIT License
Classifier: Operating System :: OS Independent
Requires-Python: >=3.6
Requires-Dist: pandas
Requires-Dist: numpy
Requires-Dist: scikit-learn
Requires-Dist: scipy
